obfuscator_ai/__init__.py
obfuscator_ai/main.py
obfuscator_ai-0.1.5.dist-info/licenses/LICENSE
tests/__init__.py
tests/test_main.py
obfuscator_ai-0.1.5.dist-info/METADATA
obfuscator_ai-0.1.5.dist-info/WHEEL
obfuscator_ai-0.1.5.dist-info/entry_points.txt
obfuscator_ai-0.1.5.dist-info/top_level.txt
obfuscator_ai-0.1.5.dist-info/RECORD
